Metadata-Version: 2.1
Name: nsegpt
Version: 0.2
Summary: A package to fetch stock data from NSE India
Home-page: https://github.com/Kaushal-developer/NSEGPT
Author: NiftyBilla
Author-email: kaushal.developer@yahoo.com
Project-URL: Bug Tracker, https://github.com/Kaushal-developer/NSEGPT/issues
Project-URL: Source Code, https://github.com/Kaushal-developer/NSEGPT
Classifier: Programming Language :: Python :: 3
Classifier: License :: OSI Approved :: MIT License
Classifier: Operating System :: OS Independent
Requires-Python: >=3.6
License-File: LICENSE
Requires-Dist: requests
